lightdiscord/__init__.py
lightdiscord/bot.py
lightdiscord-1.3.1.dist-info/LICENSE.md
lightdiscord-1.3.1.dist-info/METADATA
lightdiscord-1.3.1.dist-info/WHEEL
lightdiscord-1.3.1.dist-info/top_level.txt
lightdiscord-1.3.1.dist-info/RECORD
